alexnet_pytorch/__init__.py
alexnet_pytorch/model.py
alexnet_pytorch/utils.py
alexnet_pytorch-0.2.0.dist-info/LICENSE
alexnet_pytorch-0.2.0.dist-info/METADATA
alexnet_pytorch-0.2.0.dist-info/WHEEL
alexnet_pytorch-0.2.0.dist-info/top_level.txt
alexnet_pytorch-0.2.0.dist-info/RECORD
